Workbook

Sheet IP
A1: Date | B1: Price | C1: Log-Returns
A2: 46063 | B2: 50.5 | C2: =+LN(B2/B3) -> 0.0089508305
A3: 46062 | B3: 50.05 | C3: =+LN(B3/B4) -> 0.013072082
A4: 46059 | B4: 49.4 | C4: =+LN(B4/B5) -> 0.010582109
A5: 46058 | B5: 48.88 | C5: =+LN(B5/B6) -> 0.001638002
A6: 46057 | B6: 48.8 | C6: =+LN(B6/B7) -> 0.021960692
A7: 46056 | B7: 47.74 | C7: =+LN(B7/B8) -> -0.03093668
A8: 46055 | B8: 49.24 | C8: =+LN(B8/B9) -> 0.0073379865
A9: 46052 | B9: 48.88 | C9: =+LN(B9/B10) -> 0.0069801146
A10: 46051 | B10: 48.54 | C10: =+LN(B10/B11) -> 0.00041211622
A11: 46050 | B11: 48.52 | C11: =+LN(B11/B12) -> 0.055510967
A12: 46049 | B12: 45.9 | C12: =+LN(B12/B13) -> -0.019845345
A13: 46048 | B13: 46.82 | C13: =+LN(B13/B14) -> -0.0038371396
... A4818: 38741 | B4818: 4.9384 | C4818: =+LN(B4818/B4819) -> 0.002189338
A4819: 38740 | B4819: 4.9276

Sheet IP - FA
A1: Quarter | B1: Revenue | C1: Log-Growth | D1: Gross Profit | E1: COGS | F1: COGS Margin | G1: EBITDA | H1: OpEx
A2: 45930 | B2: 499.207 | C2: =+LN(B2/B3) -> -0.1065741 | D2: 173.845 | E2: =+B2-D2 -> 325.362 | F2: =+E2/B2 -> 0.65175769 | G2: 113.673 | H2: =+B2-E2-G2 -> 60.172 | J2: =+B2*4 -> 1996.828 | L2: =+CORREL(C2:C62,C3:C63) -> -0.036837699
A3: 45838 | B3: 555.348 | C3: =+LN(B3/B4) -> 0.062741864 | D3: 206.068 | E3: =+B3-D3 -> 349.28 | F3: =+E3/B3 -> 0.62893897 | G3: 130.333 | H3: =+B3-E3-G3 -> 75.735
A4: 45747 | B4: 521.575 | C4: =+LN(B4/B5) -> 0.062672204 | D4: 187.149 | E4: =+B4-D4 -> 334.426 | F4: =+E4/B4 -> 0.64118487 | G4: 116.644 | H4: =+B4-E4-G4 -> 70.505
A5: 45657 | B5: 489.89 | C5: =+LN(B5/B6) -> -0.0059326822 | D5: 158.502 | E5: =+B5-D5 -> 331.388 | F5: =+E5/B5 -> 0.6764539 | G5: 91.103 | H5: =+B5-E5-G5 -> 67.399
A6: 45565 | B6: 492.805 | C6: =+LN(B6/B7) -> -0.10950831 | D6: 171.788 | E6: =+B6-D6 -> 321.017 | F6: =+E6/B6 -> 0.65140776 | G6: 110.314 | H6: =+B6-E6-G6 -> 61.474
A7: 45473 | B7: 549.837 | C7: =+LN(B7/B8) -> 0.0072465143 | D7: 191.68 | E7: =+B7-D7 -> 358.157 | F7: =+E7/B7 -> 0.65138759 | G7: 123.518 | H7: =+B7-E7-G7 -> 68.162
A8: 45382 | B8: 545.867 | C8: =+LN(B8/B9) -> 0.049321845 | D8: 191.676 | E8: =+B8-D8 -> 354.191 | F8: =+E8/B8 -> 0.64885952 | G8: 126.749 | H8: =+B8-E8-G8 -> 64.927
A9: 45291 | B9: 519.597 | C9: =+LN(B9/B10) -> -0.030908993 | D9: 172.799 | E9: =+B9-D9 -> 346.798 | F9: =+E9/B9 -> 0.66743649 | G9: 109.152 | H9: =+B9-E9-G9 -> 63.647
A10: 45199 | B10: 535.908 | C10: =+LN(B10/B11) -> -0.099863336 | D10: 188.14 | E10: =+B10-D10 -> 347.768 | F10: =+E10/B10 -> 0.64893228 | G10: 129.448 | H10: =+B10-E10-G10 -> 58.692
A11: 45107 | B11: 592.189 | C11: =+LN(B11/B12) -> -0.00026339472 | D11: 207.659 | E11: =+B11-D11 -> 384.53 | F11: =+E11/B11 -> 0.64933661 | G11: 144.724 | H11: =+B11-E11-G11 -> 62.935
A12: 45016 | B12: 592.345 | C12: =+LN(B12/B13) -> 0.10552091 | D12: 211.374 | E12: =+B12-D12 -> 380.971 | F12: =+E12/B12 -> 0.64315728 | G12: 149.006 | H12: =+B12-E12-G12 -> 62.368
A13: 44926 | B13: 533.025 | C13: =+LN(B13/B14) -> 0.02734483 | D13: 188.036 | E13: =+B13-D13 -> 344.989 | F13: =+E13/B13 -> 0.64722855 | G13: 119.041 | H13: =+B13-E13-G13 -> 68.995
A14: 44834 | B14: 518.647 | C14: =+LN(B14/B15) -> -0.035913613 | D14: 176.564 | E14: =+B14-D14 -> 342.083 | F14: =+E14/B14 -> 0.65956807 | G14: 123.15 | H14: =+B14-E14-G14 -> 53.414
... A63: 40359 | B63: 110.776 | C63: =+LN(B63/B64) -> 0.10805627 | D63: 40.192 | E63: =+B63-D63 -> 70.584 | F63: =+E63/B63 -> 0.63717773 | G63: 19.233 | H63: =+B63-E63-G63 -> 20.959
A64: 40268 | B64: 99.43 | D64: 34.931 | E64: =+B64-D64 -> 64.499 | F64: =+E64/B64 -> 0.64868752 | G64: 15.996 | H64: =+B64-E64-G64 -> 18.935

Sheet IP - Cost
A1: SUMMARY OUTPUT
A3: Regression Statistics
A4: Multiple R | B4: 0.95143766
A5: R Square | B5: 0.90523361
A6: Adjusted R Square | B6: 0.90347868
A7: Standard Error | B7: 4.4648898
A8: Observations | B8: 56
A10: ANOVA
B11: df | C11: SS | D11: MS | E11: F | F11: Significance F
A12: Regression | B12: 1 | C12: 10283.042 | D12: 10283.042 | E12: 515.82229 | F12: 2.6558942e-29
A13: Residual | B13: 54 | C13: 1076.503 | D13: 19.935241
A14: Total | B14: 55 | C14: 11359.545
B16: Coefficients | C16: Standard Error | D16: t Stat | E16: P-value | F16: Lower 95% | G16: Upper 95% | H16: Lower 95.0% | I16: Upper 95.0%
A17: Intercept | B17: 12.212018 | C17: 1.3106646 | D17: 9.3174248 | E17: 7.856318e-13 | F17: 9.5842942 | G17: 14.839743 | H17: 9.5842942 | I17: 14.839743
A18: X Variable 1 | B18: 0.096248273 | C18: 0.0042378237 | D18: 22.711722 | E18: 2.6558942e-29 | F18: 0.087751948 | G18: 0.1047446 | H18: 0.087751948 | I18: 0.1047446

Sheet IP - Params
A2: Calibration Model
A3: R_0 | B3: =+'IP - FA'!B60*4 -> 464.392
A4: mu_0 | B4: =+AVERAGE('IP - FA'!C60:C63)*4 -> 0.15498078
A5: sigma | B5: =+_xlfn.STDEV.S('IP - FA'!C9:C63)/0.5 -> 0.18518354
A6: theta | B6: =+AVERAGE('IP - FA'!F9:F64) -> 0.63601184
A7: gamma | B7: =+'IP - Cost'!B18 -> 0.096248273 | C7: =+'IP - Cost'!E18 -> 2.6558942e-29 | D7: R2 | E7: =+'IP - Cost'!B5 -> 0.90523361
A8: F | B8: =+'IP - Cost'!B17 -> 12.212018 | C8: =+'IP - Cost'!E17 -> 7.856318e-13 | D8: N | E8: =+'IP - Cost'!B8 -> 56
A9: sigma_stock | B9: =+SQRT(252*_xlfn.VAR.S(IP!C:C)) -> 0.32439332
A11: Simulation Model
A12: R_0 | B12: =+'IP - FA'!B9*4 -> 2078.388
A13: mu_0 | B13: =+AVERAGE('IP - FA'!C9:C13)*4 -> 0.0014640108
A14: sigma | B14: =+B5 -> 0.18518354
A15: theta | B15: =+B6 -> 0.63601184
A16: gamma | B16: =+B7 -> 0.096248273
A17: F | B17: =+B8 -> 12.212018
A18: eta

Sheet GGG
A1: Date | B1: Last Price (R1) | C1: Log-Returns
A2: 46072 | B2: 93.225 | C2: =+LN(B2/B3) -> -0.002089529
A3: 46071 | B3: 93.42 | C3: =+LN(B3/B4) -> -0.0093757346
A4: 46070 | B4: 94.3 | C4: =+LN(B4/B5) -> -0.0039159705
A5: 46066 | B5: 94.67 | C5: =+LN(B5/B6) -> 0.0041280821
A6: 46065 | B6: 94.28 | C6: =+LN(B6/B7) -> -0.0021190938
A7: 46064 | B7: 94.48 | C7: =+LN(B7/B8) -> 0.0027556986
A8: 46063 | B8: 94.22 | C8: =+LN(B8/B9) -> 0.015724772
A9: 46062 | B9: 92.75 | C9: =+LN(B9/B10) -> -0.0001078109
A10: 46059 | B10: 92.76 | C10: =+LN(B10/B11) -> 0.0036721069
A11: 46058 | B11: 92.42 | C11: =+LN(B11/B12) -> 0.0091304982
A12: 46057 | B12: 91.58 | C12: =+LN(B12/B13) -> 0.030938876
A13: 46056 | B13: 88.79 | C13: =+LN(B13/B14) -> 0.0034974933
... A4313: 39811 | B4313: 7.4167 | C4313: =+LN(B4313/B4314) -> -0.0084985777
A4314: 39808 | B4314: 7.48

Sheet GGG - FA
A1: Quarter | B1: Revenue | C1: Log-Growth | D1: Gross Profit | E1: COGS | F1: COGS Margin | G1: EBITDA | H1: OpEx | I1: Net Debt (R2) | J1: Current Market Cap (L2)
A2: 45926 | B2: 543.358 | C2: =+LN(B2/B3) -> -0.05103137 | D2: 289.225 | E2: =+B2-D2 -> 254.133 | F2: =+E2/B2 -> 0.46770821 | G2: 188.621 | H2: =+B2-E2-G2 -> 100.604 | I2: -555.485 | J2: 14035954688
A3: 45835 | B3: 571.806 | C3: =+LN(B3/B4) -> 0.079165755 | D3: 299.53 | E3: =+B3-D3 -> 272.276 | F3: =+E3/B3 -> 0.47616849 | G3: 184.62 | H3: =+B3-E3-G3 -> 114.91 | I3: -467.774 | J3: 14398494720
A4: 45744 | B4: 528.284 | C4: =+LN(B4/B5) -> -0.037866795 | D4: 277.733 | E4: =+B4-D4 -> 250.551 | F4: =+E4/B4 -> 0.47427331 | G4: 168.721 | H4: =+B4-E4-G4 -> 109.012 | I4: -471.154 | J4: 14025940992
A5: 45653 | B5: 548.672 | C5: =+LN(B5/B6) -> 0.055188535 | D5: 279.28 | E5: =+B5-D5 -> 269.392 | F5: =+E5/B5 -> 0.49098915 | G5: 154.714 | H5: =+B5-E5-G5 -> 124.566 | I5: -611.678 | J5: 14207003648
A6: 45562 | B6: 519.212 | C6: =+LN(B6/B7) -> -0.063485049 | D6: 276.13 | E6: =+B6-D6 -> 243.082 | F6: =+E6/B6 -> 0.46817485 | G6: 168.452 | H6: =+B6-E6-G6 -> 107.678 | I6: -717.692 | J6: 14805143552
A7: 45471 | B7: 553.243 | C7: =+LN(B7/B8) -> 0.11693454 | D7: 300.854 | E7: =+B7-D7 -> 252.389 | F7: =+E7/B7 -> 0.45619917 | G7: 181.168 | H7: =+B7-E7-G7 -> 119.686 | I7: -618.968 | J7: 13409092608
A8: 45380 | B8: 492.189 | C8: =+LN(B8/B9) -> -0.14086669 | D8: 266.197 | E8: =+B8-D8 -> 225.992 | F8: =+E8/B8 -> 0.45915695 | G8: 152.512 | H8: =+B8-E8-G8 -> 113.685 | I8: -575.771
A9: 45289 | B9: 566.643 | C9: =+LN(B9/B10) -> 0.048767928 | D9: 299.942 | E9: =+B9-D9 -> 266.701 | F9: =+E9/B9 -> 0.47066848 | G9: 190.076 | H9: =+B9-E9-G9 -> 109.866 | I9: -487.888 | J9: 14644054016
A10: 45198 | B10: 539.672 | C10: =+LN(B10/B11) -> -0.03633932 | D10: 284.524 | E10: =+B10-D10 -> 255.148 | F10: =+E10/B10 -> 0.47278347 | G10: 181.251 | H10: =+B10-E10-G10 -> 103.273 | I10: -468.858 | J10: 12316193792
A11: 45107 | B11: 559.644 | C11: =+LN(B11/B12) -> 0.055092008 | D11: 291.415 | E11: =+B11-D11 -> 268.229 | F11: =+E11/B11 -> 0.47928505 | G11: 175.182 | H11: =+B11-E11-G11 -> 116.233 | I11: -367.065 | J11: 14536186880
A12: 45016 | B12: 529.646 | C12: =+LN(B12/B13) -> -0.046840333 | D12: 285.14 | E12: =+B12-D12 -> 244.506 | F12: =+E12/B12 -> 0.46164042 | G12: 174.655 | H12: =+B12-E12-G12 -> 110.485 | I12: -247.568 | J12: 12265290752
A13: 44925 | B13: 555.045 | C13: =+LN(B13/B14) -> 0.017082443 | D13: 272.816 | E13: =+B13-D13 -> 282.229 | F13: =+E13/B13 -> 0.50847949 | G13: 170.282 | H13: =+B13-E13-G13 -> 102.534 | I13: -212.61 | J13: 11335261184
A14: 44834 | B14: 545.644 | C14: =+LN(B14/B15) -> -0.0053062158 | D14: 261.088 | E14: =+B14-D14 -> 284.556 | F14: =+E14/B14 -> 0.52150486 | G14: 159.919 | H14: =+B14-E14-G14 -> 101.169 | I14: -265.835 | J14: 10138477568
A15: 44743 | B15: 548.547 | C15: =+LN(B15/B16) -> 0.10416069 | D15: 269.06 | E15: =+B15-D15 -> 279.487 | F15: =+E15/B15 -> 0.5095042 | G15: 164.563 | H15: =+B15-E15-G15 -> 104.497 | I15: -250.341 | J15: 10068997120
A16: 44652 | B16: 494.285 | C16: =+LN(B16/B17) -> -0.087751061 | D16: 254.475 | E16: =+B16-D16 -> 239.81 | F16: =+E16/B16 -> 0.48516544 | G16: 143.933 | H16: =+B16-E16-G16 -> 110.542 | I16: -231.669 | J16: 11979243520
A17: 44561 | B17: 539.619 | C17: =+LN(B17/B18) -> 0.10322364 | D17: 274.557 | E17: =+B17-D17 -> 265.062 | F17: =+E17/B17 -> 0.49120213 | G17: 159.074 | H17: =+B17-E17-G17 -> 115.483 | I17: -398.19 | J17: 13702624256
A18: 44463 | B18: 486.696 | C18: =+LN(B18/B19) -> -0.041194724 | D18: 248.234 | E18: =+B18-D18 -> 238.462 | F18: =+E18/B18 -> 0.48996088 | G18: 139.633 | H18: =+B18-E18-G18 -> 108.601 | I18: -363.707 | J18: 12474310656
A19: 44372 | B19: 507.164 | C19: =+LN(B19/B20) -> 0.11045312 | D19: 263.824 | E19: =+B19-D19 -> 243.34 | F19: =+E19/B19 -> 0.47980535 | G19: 149.14 | H19: =+B19-E19-G19 -> 114.684 | I19: -278.258 | J19: 12704241664
A20: 44281 | B20: 454.129 | C20: =+LN(B20/B21) -> -0.035074539 | D20: 247.334 | E20: =+B20-D20 -> 206.795 | F20: =+E20/B20 -> 0.45536621 | G20: 142.801 | H20: =+B20-E20-G20 -> 104.533 | I20: -239.582 | J20: 12152790016
A21: 44190 | B21: 470.34 | C21: =+LN(B21/B22) -> 0.068236866 | D21: 244.824 | E21: =+B21-D21 -> 225.516 | F21: =+E21/B21 -> 0.47947442 | G21: 146.743 | H21: =+B21-E21-G21 -> 98.081 | I21: -166.324
A22: 44099 | B22: 439.316 | C22: =+LN(B22/B23) -> 0.18015145 | D22: 228.953 | E22: =+B22-D22 -> 210.363 | F22: =+E22/B22 -> 0.47884211 | G22: 138.753 | H22: =+B22-E22-G22 -> 90.2 | I22: -75.205 | J22: 10087660544
A23: 44008 | B23: 366.892 | C23: =+LN(B23/B24) -> -0.018029846 | D23: 182.529 | E23: =+B23-D23 -> 184.363 | F23: =+E23/B23 -> 0.50249937 | G23: 58.677 | H23: =+B23-E23-G23 -> 123.852 | I23: 18.571 | J23: 7801788928
A24: 43917 | B24: 373.567 | C24: =+LN(B24/B25) -> -0.098634463 | D24: 198.631 | E24: =+B24-D24 -> 174.936 | F24: =+E24/B24 -> 0.46828547 | G24: 102.874 | H24: =+B24-E24-G24 -> 95.757 | I24: 21.412 | J24: 7664221184
A25: 43826 | B25: 412.292 | C25: =+LN(B25/B26) -> 0.028880751 | D25: 209.381 | E25: =+B25-D25 -> 202.911 | F25: =+E25/B25 -> 0.49215362 | G25: 119.579 | H25: =+B25-E25-G25 -> 89.802 | I25: -17.077 | J25: 8702580736
A26: 43735 | B26: 400.555 | C26: =+LN(B26/B27) -> -0.067038172 | D26: 207.379 | E26: =+B26-D26 -> 193.176 | F26: =+E26/B26 -> 0.48227085 | G26: 118.513 | H26: =+B26-E26-G26 -> 88.866 | I26: 52.209 | J26: 7626324480
A27: 43644 | B27: 428.328 | C27: =+LN(B27/B28) -> 0.056323229 | D27: 226.954 | E27: =+B27-D27 -> 201.374 | F27: =+E27/B27 -> 0.47013971 | G27: 127.435 | H27: =+B27-E27-G27 -> 99.519 | I27: 114.632 | J27: 8355885056
A28: 43553 | B28: 404.87 | C28: =+LN(B28/B29) -> -0.0038653679 | D28: 216.042 | E28: =+B28-D28 -> 188.828 | F28: =+E28/B28 -> 0.46639168 | G28: 119.34 | H28: =+B28-E28-G28 -> 96.702 | I28: 172.269 | J28: 8196068864
A29: 43462 | B29: 406.438 | C29: =+LN(B29/B30) -> -0.023100006 | D29: 208.756 | E29: =+B29-D29 -> 197.682 | F29: =+E29/B29 -> 0.48637677 | G29: 108.758 | H29: =+B29-E29-G29 -> 99.998 | I29: 145.356 | J29: 6843889664
A30: 43371 | B30: 415.936 | C30: =+LN(B30/B31) -> -0.02054549 | D30: 221.459 | E30: =+B30-D30 -> 194.477 | F30: =+E30/B30 -> 0.46756472 | G30: 126.594 | H30: =+B30-E30-G30 -> 94.865 | I30: 132.795 | J30: 7745731072
A31: 43280 | B31: 424.57 | C31: =+LN(B31/B32) -> 0.043866957 | D31: 229.903 | E31: =+B31-D31 -> 194.667 | F31: =+E31/B31 -> 0.4585039 | G31: 124.482 | H31: =+B31-E31-G31 -> 105.421 | I31: 193.99 | J31: 7579143168
A32: 43189 | B32: 406.348 | C32: =+LN(B32/B33) -> 0.08065998 | D32: 222.421 | E32: =+B32-D32 -> 183.927 | F32: =+E32/B32 -> 0.4526342 | G32: 124.347 | H32: =+B32-E32-G32 -> 98.074 | I32: 183.294
A33: 43098 | B33: 374.859 | C33: =+LN(B33/B34) -> -0.013126438 | D33: 200.767 | E33: =+B33-D33 -> 174.092 | F33: =+E33/B33 -> 0.46441996 | G33: 101.428 | H33: =+B33-E33-G33 -> 99.339 | I33: 128.951 | J33: 7614595584
A34: 43007 | B34: 379.812 | C34: =+LN(B34/B35) -> 0.00086659341 | D34: 204.08 | E34: =+B34-D34 -> 175.732 | F34: =+E34/B34 -> 0.46268154 | G34: 112.693 | H34: =+B34-E34-G34 -> 91.387 | I34: 166.215 | J34: 6926145024
A35: 42916 | B35: 379.483 | C35: =+LN(B35/B36) -> 0.10813039 | D35: 204.51 | E35: =+B35-D35 -> 174.973 | F35: =+E35/B35 -> 0.46108258 | G35: 111.678 | H35: =+B35-E35-G35 -> 92.832 | I35: 246.635 | J35: 6070722560
A36: 42825 | B36: 340.59 | C36: =+LN(B36/B37) -> -0.024573014 | D36: 185.845 | E36: =+B36-D36 -> 154.745 | F36: =+E36/B36 -> 0.45434393 | G36: 98.529 | H36: =+B36-E36-G36 -> 87.316 | I36: 310.467 | J36: 5203341824
A37: 42734 | B37: 349.063 | C37: =+LN(B37/B38) -> 0.064705267 | D37: 184.704 | E37: =+B37-D37 -> 164.359 | F37: =+E37/B37 -> 0.4708577 | G37: -95.432 | H37: =+B37-E37-G37 -> 280.136 | I37: 262.233 | J37: 4626783232
A38: 42636 | B38: 327.192 | C38: =+LN(B38/B39) -> -0.062017329 | D38: 176.598 | E38: =+B38-D38 -> 150.594 | F38: =+E38/B38 -> 0.46026186 | G38: 93.81 | H38: =+B38-E38-G38 -> 82.788 | I38: 310.838 | J38: 4094633728
A39: 42545 | B39: 348.126 | C39: =+LN(B39/B40) -> 0.13254127 | D39: 185.141 | E39: =+B39-D39 -> 162.985 | F39: =+E39/B39 -> 0.46817819 | G39: 90.832 | H39: =+B39-E39-G39 -> 94.309 | I39: 398.937 | J39: 4308972544
A40: 42454 | B40: 304.912 | C40: =+LN(B40/B41) -> -0.065514351 | D40: 161.796 | E40: =+B40-D40 -> 143.116 | F40: =+E40/B40 -> 0.46936821 | G40: 72.959 | H40: =+B40-E40-G40 -> 88.837 | I40: 435.688
A41: 42363 | B41: 325.557 | C41: =+LN(B41/B42) -> 0.020390347 | D41: 171.752 | E41: =+B41-D41 -> 153.805 | F41: =+E41/B41 -> 0.47243647 | G41: 87.397 | H41: =+B41-E41-G41 -> 84.355 | I41: 356.301
A42: 42272 | B42: 318.986 | C42: =+LN(B42/B43) -> -0.050441954 | D42: 170.196 | E42: =+B42-D42 -> 148.79 | F42: =+E42/B42 -> 0.4664468 | G42: 88.244 | H42: =+B42-E42-G42 -> 81.952 | I42: 332.33 | J42: 3836669440
A43: 42181 | B43: 335.489 | C43: =+LN(B43/B44) -> 0.09052477 | D43: 180.623 | E43: =+B43-D43 -> 154.866 | F43: =+E43/B43 -> 0.46161275 | G43: 95.05 | H43: =+B43-E43-G43 -> 85.573 | I43: 266.506 | J43: 4250047744
A44: 42090 | B44: 306.453 | C44: =+LN(B44/B45) -> 0.0014629577 | D44: 162.129 | E44: =+B44-D44 -> 144.324 | F44: =+E44/B44 -> 0.47094987 | G44: 76.041 | H44: =+B44-E44-G44 -> 86.088 | I44: 369.608 | J44: 4188780032
A45: 41999 | B45: 306.005 | C45: =+LN(B45/B46) -> 0.011143376 | D45: 164.76 | E45: =+B45-D45 -> 141.245 | F45: =+E45/B45 -> 0.46157743 | G45: 77.359 | H45: =+B45-E45-G45 -> 87.401 | I45: 174.593 | J45: 4842561024
A46: 41908 | B46: 302.614 | C46: =+LN(B46/B47) -> -0.063796997 | D46: 165.814 | E46: =+B46-D46 -> 136.8 | F46: =+E46/B46 -> 0.45206104 | G46: 88.201 | H46: =+B46-E46-G46 -> 77.613 | I46: 64.407 | J46: 4377647616
A47: 41817 | B47: 322.549 | C47: =+LN(B47/B48) -> 0.10650518 | D47: 176.85 | E47: =+B47-D47 -> 145.699 | F47: =+E47/B47 -> 0.45171121 | G47: 94.913 | H47: =+B47-E47-G47 -> 81.937 | I47: 84.024 | J47: 4713500160
A48: 41726 | B48: 289.962 | C48: =+LN(B48/B49) -> 0.064230942 | D48: 159.312 | E48: =+B48-D48 -> 130.65 | F48: =+E48/B48 -> 0.45057628 | G48: 83.967 | H48: =+B48-E48-G48 -> 75.345 | I48: 67.68 | J48: 4475798016
A49: 41635 | B49: 271.923 | C49: =+LN(B49/B50) -> -0.018624914 | D49: 147.199 | E49: =+B49-D49 -> 124.724 | F49: =+E49/B49 -> 0.45867396 | G49: 72.897 | H49: =+B49-E49-G49 -> 74.302 | I49: -24.099 | J49: 4765152256
A50: 41544 | B50: 277.035 | C50: =+LN(B50/B51) -> -0.031917886 | D50: 150.873 | E50: =+B50-D50 -> 126.162 | F50: =+E50/B50 -> 0.45540094 | G50: 78.837 | H50: =+B50-E50-G50 -> 72.036 | I50: -25.786 | J50: 4504117248
A51: 41453 | B51: 286.02 | C51: =+LN(B51/B52) -> 0.06117937 | D51: 158.739 | E51: =+B51-D51 -> 127.281 | F51: =+E51/B51 -> 0.44500734 | G51: 84.582 | H51: =+B51-E51-G51 -> 74.157 | I51: 20.041 | J51: 3872307968
A52: 41362 | B52: 269.046 | C52: =+LN(B52/B53) -> 0.058816622 | D52: 150.644 | E52: =+B52-D52 -> 118.402 | F52: =+E52/B52 -> 0.44008088 | G52: 80.769 | H52: =+B52-E52-G52 -> 69.875 | I52: 64.66
A53: 41271 | B53: 253.678 | C53: =+LN(B53/B54) -> -0.010953751 | D53: 138.888 | E53: =+B53-D53 -> 114.79 | F53: =+E53/B53 -> 0.45250278 | G53: 68.22 | H53: =+B53-E53-G53 -> 70.668 | I53: 106.68 | J53: 3085222144
A54: 41180 | B54: 256.472 | C54: =+LN(B54/B55) -> -0.044653815 | D54: 139.933 | E54: =+B54-D54 -> 116.539 | F54: =+E54/B54 -> 0.45439268 | G54: 66.394 | H54: =+B54-E54-G54 -> 73.539 | I54: 143.103 | J54: 3042794752
A55: 41089 | B55: 268.184 | C55: =+LN(B55/B56) -> 0.13583097 | D55: 139.53 | E55: =+B55-D55 -> 128.654 | F55: =+E55/B55 -> 0.47972288 | G55: 62.781 | H55: =+B55-E55-G55 -> 76.749 | I55: 183.615 | J55: 2785351680
A56: 40998 | B56: 234.122 | C56: =+LN(B56/B57) -> 0.082445338 | D56: 132.179 | E56: =+B56-D56 -> 101.943 | F56: =+E56/B56 -> 0.43542683 | G56: 66.044 | H56: =+B56-E56-G56 -> 66.135 | I56: -16.251 | J56: 3175598592
A57: 40907 | B57: 215.594 | C57: =+LN(B57/B58) -> -0.053080475 | D57: 117.013 | E57: =+B57-D57 -> 98.581 | F57: =+E57/B57 -> 0.45725298 | G57: 53.563 | H57: =+B57-E57-G57 -> 63.45 | I57: 5.508 | J57: 2440519680
A58: 40816 | B58: 227.347 | C58: =+LN(B58/B59) -> -0.031672958 | D58: 126.349 | E58: =+B58-D58 -> 100.998 | F58: =+E58/B58 -> 0.44424602 | G58: 65.568 | H58: =+B58-E58-G58 -> 60.781 | I58: 33.256 | J58: 2077419008
A59: 40725 | B59: 234.663 | C59: =+LN(B59/B60) -> 0.075128942 | D59: 132.446 | E59: =+B59-D59 -> 102.217 | F59: =+E59/B59 -> 0.43559061 | G59: 67.37 | H59: =+B59-E59-G59 -> 65.076 | I59: 44.668 | J59: 3125242880
A60: 40634 | B60: 217.679 | C60: =+LN(B60/B61) -> 0.098331567 | D60: 124.397 | E60: =+B60-D60 -> 93.282 | F60: =+E60/B60 -> 0.42853008 | G60: 65.496 | H60: =+B60-E60-G60 -> 58.901 | I60: 58.683 | J60: 2712574720
A61: 40543 | B61: 197.293 | C61: =+LN(B61/B62) -> 0.037860617 | D61: 107.672 | E61: =+B61-D61 -> 89.621 | F61: =+E61/B61 -> 0.45425332 | G61: 46.28 | H61: =+B61-E61-G61 -> 61.392 | I61: 68.847 | J61: 2362187008
A62: 40445 | B62: 189.963 | C62: =+LN(B62/B63) -> -0.011124284 | D62: 104.558 | E62: =+B62-D62 -> 85.405 | F62: =+E62/B62 -> 0.44958755 | G62: 51.6 | H62: =+B62-E62-G62 -> 52.958 | I62: 91.4 | J62: 1855638400
A63: 40354 | B63: 192.088 | C63: =+LN(B63/B64) -> 0.15370047 | D63: 101.92 | E63: =+B63-D63 -> 90.168 | F63: =+E63/B63 -> 0.46940985 | G63: 47.95 | H63: =+B63-E63-G63 -> 53.97 | I63: 88.721 | J63: 1818726016
A64: 40263 | B64: 164.721 | D64: 89.295 | E64: =+B64-D64 -> 75.426 | F64: =+E64/B64 -> 0.45790154 | G64: 41.284 | H64: =+B64-E64-G64 -> 48.011 | I64: 82.418 | J64: 1891925504

Sheet GGG - Cost
A1: SUMMARY OUTPUT
A3: Regression Statistics
A4: Multiple R | B4: 0.50389576
A5: R Square | B5: 0.25391094
A6: Adjusted R Square | B6: 0.24009447
A7: Standard Error | B7: 27.329925
A8: Observations | B8: 56
A10: ANOVA
B11: df | C11: SS | D11: MS | E11: F | F11: Significance F
A12: Regression | B12: 1 | C12: 13726.55 | D12: 13726.55 | E12: 18.377418 | F12: 7.5213517e-05
A13: Residual | B13: 54 | C13: 40333.94 | D13: 746.92482
A14: Total | B14: 55 | C14: 54060.49
B16: Coefficients | C16: Standard Error | D16: t Stat | E16: P-value | F16: Lower 95% | G16: Upper 95% | H16: Lower 95.0% | I16: Upper 95.0%
A17: Intercept | B17: 39.675305 | C17: 12.542001 | D17: 3.163395 | E17: 0.0025601405 | F17: 14.530106 | G17: 64.820504 | H17: 14.530106 | I17: 64.820504
A18: X Variable 1 | B18: 0.14158844 | C18: 0.033028249 | D18: 4.2868891 | E18: 7.5213517e-05 | F18: 0.075370788 | G18: 0.20780609 | H18: 0.075370788 | I18: 0.20780609

Sheet GGG - Params
A2: Calibration Model
A3: R_0 | B3: =+'GGG - FA'!B60*4 -> 870.716
A4: mu_0 | B4: =+AVERAGE('GGG - FA'!C60:C63)*4 -> 0.27876837
A5: sigma | B5: =+_xlfn.STDEV.S('GGG - FA'!C9:C63)/0.5 -> 0.13452777
A6: theta | B6: =+AVERAGE('GGG - FA'!F9:F64) -> 0.46691159
A7: gamma | B7: =+'GGG - Cost'!B18 -> 0.14158844 | C7: =+'GGG - Cost'!E18 -> 7.5213517e-05 | D7: R2 | E7: =+'GGG - Cost'!B5 -> 0.25391094
A8: F | B8: =+'GGG - Cost'!B17 -> 39.675305 | C8: =+'GGG - Cost'!E17 -> 0.0025601405 | D8: N | E8: =+'GGG - Cost'!B8 -> 56
A9: sigma_stock | B9: =+SQRT(252*_xlfn.VAR.S(GGG!C:C)) -> 0.27381119
A11: Simulation Model
A12: R_0 | B12: =+'GGG - FA'!B9*4 -> 2266.572
A13: mu_0 | B13: =+AVERAGE('GGG - FA'!C9:C13)*4 -> 0.030210182
A14: sigma | B14: =+B5 -> 0.13452777
A15: theta | B15: =+B6 -> 0.46691159
A16: gamma | B16: =+B7 -> 0.14158844
A17: F | B17: =+B8 -> 39.675305
A18: eta

Sheet ALFA
A1: Date | B1: Last Price (R1) | C1: Log-Returns
A2: 46072 | B2: 521.8 | C2: =+LN(B2/B3) -> 0
A3: 46071 | B3: 521.8 | C3: =+LN(B3/B4) -> 0.010402714
A4: 46070 | B4: 516.4 | C4: =+LN(B4/B5) -> 0.0081664852
A5: 46069 | B5: 512.2 | C5: =+LN(B5/B6) -> 0.0058743071
A6: 46066 | B6: 509.2 | C6: =+LN(B6/B7) -> -0.001961939
A7: 46065 | B7: 510.2 | C7: =+LN(B7/B8) -> -0.0078094891
A8: 46064 | B8: 514.2 | C8: =+LN(B8/B9) -> 0.0085938029
A9: 46063 | B9: 509.8 | C9: =+LN(B9/B10) -> -0.0011762401
A10: 46062 | B10: 510.4 | C10: =+LN(B10/B11) -> 0
A11: 46059 | B11: 510.4 | C11: =+LN(B11/B12) -> 0.0074729945
A12: 46058 | B12: 506.6 | C12: =+LN(B12/B13) -> -0.005511825
A13: 46057 | B13: 509.4 | C13: =+LN(B13/B14) -> 0.0078833676
... A412: 45474 | B412: 469.9 | C412: =+LN(B412/B413) -> 0.01241986
A413: 45471 | B413: 464.1
A414: 45470 | B414: 463.4 | C414: =+LN(B414/B415) -> -0.013290657
A415: 45469 | B415: 469.6 | C415: =+LN(B415/B416) -> 0.0094138479
A416: 45468 | B416: 465.2 | C416: =+LN(B416/B417) -> -0.013451681
A417: 45467 | B417: 471.5 | C417: =+LN(B417/B418) -> 0.013021851
A418: 45463 | B418: 465.4 | C418: =+LN(B418/B419) -> 0.0051701968
A419: 45462 | B419: 463 | C419: =+LN(B419/B420) -> -0.0071021497
A420: 45461 | B420: 466.3 | C420: =+LN(B420/B421) -> -0.0025701449
A421: 45460 | B421: 467.5 | C421: =+LN(B421/B422) -> 0.0062225284
A422: 45457 | B422: 464.6 | C422: =+LN(B422/B423) -> -0.035313956
A423: 45456 | B423: 481.3 | C423: =+LN(B423/B424) -> -0.0060072682
A424: 45455 | B424: 484.2 | C424: =+LN(B424/B425) -> 0.01834149
A425: 45454 | B425: 475.4 | C425: =+LN(B425/B426) -> -0.0098378606
... A473: 45379 | B473: 420.8 | C473: =+LN(B473/B474) -> -0.0082830908
A474: 45378 | B474: 424.3
A475: 45377 | B475: 426.5 | C475: =+LN(B475/B476) -> -0.0093349569
A476: 45376 | B476: 430.5 | C476: =+LN(B476/B477) -> -0.017728103
A477: 45373 | B477: 438.2 | C477: =+LN(B477/B478) -> 0.0013701761
A478: 45372 | B478: 437.6 | C478: =+LN(B478/B479) -> 0.022182056
A479: 45371 | B479: 428 | C479: =+LN(B479/B480) -> 0.012933749
A480: 45370 | B480: 422.5 | C480: =+LN(B480/B481) -> 0.0071259209
A481: 45369 | B481: 419.5 | C481: =+LN(B481/B482) -> -0.0042816431
A482: 45366 | B482: 421.3 | C482: =+LN(B482/B483) -> 0.014825714
A483: 45365 | B483: 415.1 | C483: =+LN(B483/B484) -> 0.0053140222
A484: 45364 | B484: 412.9 | C484: =+LN(B484/B485) -> -0.0021773324
A485: 45363 | B485: 413.8 | C485: =+LN(B485/B486) -> 0.013870523
A486: 45362 | B486: 408.1 | C486: =+LN(B486/B487) -> 0.010592537
... A537: 45288 | B537: 404.7 | C537: =+LN(B537/B538) -> -0.0017281821
A538: 45287 | B538: 405.4
A539: 45282 | B539: 400.8 | C539: =+LN(B539/B540) -> -0.0014958866
A540: 45281 | B540: 401.4 | C540: =+LN(B540/B541) -> -0.0034817245
A541: 45280 | B541: 402.8 | C541: =+LN(B541/B542) -> 0.0042293881
A542: 45279 | B542: 401.1 | C542: =+LN(B542/B543) -> 0.019383867
A543: 45278 | B543: 393.4 | C543: =+LN(B543/B544) -> -0.0068397987
A544: 45275 | B544: 396.1 | C544: =+LN(B544/B545) -> 0.010915199
A545: 45274 | B545: 391.8 | C545: =+LN(B545/B546) -> 0.01569164
A546: 45273 | B546: 385.7 | C546: =+LN(B546/B547) -> -0.0087765148
A547: 45272 | B547: 389.1 | C547: =+LN(B547/B548) -> 0.0018006436
A548: 45271 | B548: 388.4 | C548: =+LN(B548/B549) -> 0.0082730565
A549: 45268 | B549: 385.2 | C549: =+LN(B549/B550) -> 0.0083420713
A550: 45267 | B550: 382 | C550: =+LN(B550/B551) -> -0.0088611474
... A601: 45196 | B601: 363.8 | C601: =+LN(B601/B602) -> -0.0046620131
A602: 45195 | B602: 365.5
A603: 45194 | B603: 365.3 | C603: =+LN(B603/B604) -> -0.0019143996
A604: 45191 | B604: 366 | C604: =+LN(B604/B605) -> -0.0040899853
A605: 45190 | B605: 367.5 | C605: =+LN(B605/B606) -> -0.021535153
A606: 45189 | B606: 375.5 | C606: =+LN(B606/B607) -> 0.013405026
A607: 45188 | B607: 370.5 | C607: =+LN(B607/B608) -> -0.0037715562
A608: 45187 | B608: 371.9 | C608: =+LN(B608/B609) -> -0.0040252302
A609: 45184 | B609: 373.4 | C609: =+LN(B609/B610) -> 0.0053705822
A610: 45183 | B610: 371.4 | C610: =+LN(B610/B611) -> 0.0018865388
A611: 45182 | B611: 370.7 | C611: =+LN(B611/B612) -> -0.0026939671
A612: 45181 | B612: 371.7 | C612: =+LN(B612/B613) -> -0.013362037
A613: 45180 | B613: 376.7 | C613: =+LN(B613/B614) -> -0.021534446
A614: 45177 | B614: 384.9 | C614: =+LN(B614/B615) -> -0.0054411327
... A790: 44922 | B790: 306 | C790: =+LN(B790/B791) -> 0.013820556
A791: 44918 | B791: 301.8
A792: 44917 | B792: 299.9 | C792: =+LN(B792/B793) -> -0.023072876
A793: 44916 | B793: 306.9 | C793: =+LN(B793/B794) -> 0.022739487
A794: 44915 | B794: 300 | C794: =+LN(B794/B795) -> 0
A795: 44914 | B795: 300 | C795: =+LN(B795/B796) -> 0.0016680571
A796: 44911 | B796: 299.5 | C796: =+LN(B796/B797) -> -0.02505901
A797: 44910 | B797: 307.1 | C797: =+LN(B797/B798) -> -0.029517703
A798: 44909 | B798: 316.3 | C798: =+LN(B798/B799) -> 0.0060250698
A799: 44908 | B799: 314.4 | C799: =+LN(B799/B800) -> 0.022841591
A800: 44907 | B800: 307.3 | C800: =+LN(B800/B801) -> -0.0025999365
A801: 44904 | B801: 308.1 | C801: =+LN(B801/B802) -> 0.02964644
A802: 44903 | B802: 299.1 | C802: =+LN(B802/B803) -> -0.021171813
A803: 44902 | B803: 305.5 | C803: =+LN(B803/B804) -> -0.004897969
... A1044: 44553 | B1044: 360.4 | C1044: =+LN(B1044/B1045) -> 0.015660275
A1045: 44552 | B1045: 354.8
A1046: 44551 | B1046: 349 | C1046: =+LN(B1046/B1047) -> 0.021724243
A1047: 44550 | B1047: 341.5 | C1047: =+LN(B1047/B1048) -> -0.00087809167
A1048: 44547 | B1048: 341.8 | C1048: =+LN(B1048/B1049) -> -0.0064158867
A1049: 44546 | B1049: 344 | C1049: =+LN(B1049/B1050) -> 0.00029073994
A1050: 44545 | B1050: 343.9 | C1050: =+LN(B1050/B1051) -> -0.0055096558
A1051: 44544 | B1051: 345.8 | C1051: =+LN(B1051/B1052) -> -0.025411789
A1052: 44543 | B1052: 354.7 | C1052: =+LN(B1052/B1053) -> -0.0030964135
A1053: 44540 | B1053: 355.8 | C1053: =+LN(B1053/B1054) -> -0.0044868275
A1054: 44539 | B1054: 357.4 | C1054: =+LN(B1054/B1055) -> -0.006414748
A1055: 44538 | B1055: 359.7 | C1055: =+LN(B1055/B1056) -> -0.0030534375
A1056: 44537 | B1056: 360.8 | C1056: =+LN(B1056/B1057) -> 0.035833993
A1057: 44536 | B1057: 348.1 | C1057: =+LN(B1057/B1058) -> 0.013011605
... A1298: 44186 | B1298: 220.3 | C1298: =+LN(B1298/B1299) -> -0.021110148
A1299: 44183 | B1299: 225
A1300: 44182 | B1300: 223.6 | C1300: =+LN(B1300/B1301) -> -0.020801812
...

Sheet ALFA - FA
A1: Quarter | B1: Revenue | C1: Log-Growth | D1: Gross Profit | E1: COGS | F1: COGS Margin | G1: EBITDA | H1: OpEx | I1: Net Debt (R2) | J1: Current Market Cap (L2)
A2: 45930 | B2: 17243 | C2: =+LN(B2/B3) -> 0.024897064 | D2: 6356 | E2: =+B2-D2 -> 10887 | F2: =+E2/B2 -> 0.63138665 | G2: 3674 | H2: =+B2-E2-G2 -> 2682 | I2: 15521 | J2: 177068998656
A3: 45838 | B3: 16819 | C3: =+LN(B3/B4) -> 0.021272284 | D3: 6320 | E3: =+B3-D3 -> 10499 | F3: =+E3/B3 -> 0.6242345 | G3: 3484 | H3: =+B3-E3-G3 -> 2836 | I3: 7172 | J3: 164421206016
A4: 45747 | B4: 16465 | C4: =+LN(B4/B5) -> -0.10615583 | D4: 6057 | E4: =+B4-D4 -> 10408 | F4: =+E4/B4 -> 0.63212876 | G4: 3381 | H4: =+B4-E4-G4 -> 2676 | I4: 3642 | J4: 177275650048
A5: 45657 | B5: 18309 | C5: =+LN(B5/B6) -> 0.12188779 | D5: 6297 | E5: =+B5-D5 -> 12012 | F5: =+E5/B5 -> 0.65607078 | G5: 3418 | H5: =+B5-E5-G5 -> 2879 | I5: 5494
A6: 45565 | B6: 16208 | C6: =+LN(B6/B7) -> -0.078465795 | D6: 5842 | E6: =+B6-D6 -> 10366 | F6: =+E6/B6 -> 0.63956071 | G6: 3214 | H6: =+B6-E6-G6 -> 2628 | I6: 7732 | J6: 201537912832
A7: 45473 | B7: 17531 | C7: =+LN(B7/B8) -> 0.16220693 | D7: 5858 | E7: =+B7-D7 -> 11673 | F7: =+E7/B7 -> 0.66584907 | G7: 3348 | H7: =+B7-E7-G7 -> 2510 | I7: 9524
A8: 45382 | B8: 14906 | C8: =+LN(B8/B9) -> -0.17962326 | D8: 5210 | E8: =+B8-D8 -> 9696 | F8: =+E8/B8 -> 0.65047632 | G8: 2840 | H8: =+B8-E8-G8 -> 2370 | I8: 8663
A9: 45291 | B9: 17839 | C9: =+LN(B9/B10) -> 0.1234045 | D9: 5642 | E9: =+B9-D9 -> 12197 | F9: =+E9/B9 -> 0.68372667 | G9: 3266 | H9: =+B9-E9-G9 -> 2376 | I9: 10345
A10: 45199 | B10: 15768 | C10: =+LN(B10/B11) -> -0.007077886 | D10: 5233 | E10: =+B10-D10 -> 10535 | F10: =+E10/B10 -> 0.66812532 | G10: 3002 | H10: =+B10-E10-G10 -> 2231 | I10: 12108
A11: 45107 | B11: 15880 | C11: =+LN(B11/B12) -> 0.11810582 | D11: 5144 | E11: =+B11-D11 -> 10736 | F11: =+E11/B11 -> 0.67607053 | G11: 2743 | H11: =+B11-E11-G11 -> 2401 | I11: 14484 | J11: 162437234688
A12: 45016 | B12: 14111 | C12: =+LN(B12/B13) -> -0.15543558 | D12: 4865 | E12: =+B12-D12 -> 9246 | F12: =+E12/B12 -> 0.65523351 | G12: 2717 | H12: =+B12-E12-G12 -> 2148 | I12: 12078 | J12: 153010257920
A13: 44926 | B13: 16484 | C13: =+LN(B13/B14) -> 0.22338624 | D13: 5177 | E13: =+B13-D13 -> 11307 | F13: =+E13/B13 -> 0.68593788 | G13: 2372 | H13: =+B13-E13-G13 -> 2805 | I13: 13493
A14: 44834 | B14: 13184 | C14: =+LN(B14/B15) -> 0.10650734 | D14: 4274 | E14: =+B14-D14 -> 8910 | F14: =+E14/B14 -> 0.67581917 | G14: 2416 | H14: =+B14-E14-G14 -> 1858 | I14: 12333 | J14: 115223306240
A15: 44742 | B15: 11852 | C15: =+LN(B15/B16) -> 0.11022853 | D15: 4263 | E15: =+B15-D15 -> 7589 | F15: =+E15/B15 -> 0.64031387 | G15: 2244 | H15: =+B15-E15-G15 -> 2019 | I15: 8381 | J15: 102062022656
A16: 44651 | B16: 10615 | C16: =+LN(B16/B17) -> -0.096636752 | D16: 3932 | E16: =+B16-D16 -> 6683 | F16: =+E16/B16 -> 0.62958078 | G16: 1831 | H16: =+B16-E16-G16 -> 2101 | I16: 5565 | J16: 136449138688
A17: 44561 | B17: 11692 | C17: =+LN(B17/B18) -> 0.12919109 | D17: 4035 | E17: =+B17-D17 -> 7657 | F17: =+E17/B17 -> 0.65489223 | G17: 2290 | H17: =+B17-E17-G17 -> 1745 | I17: 7155
A18: 44469 | B18: 10275 | C18: =+LN(B18/B19) -> 0.029631798 | D18: 3636 | E18: =+B18-D18 -> 6639 | F18: =+E18/B18 -> 0.64613139 | G18: 2149 | H18: =+B18-E18-G18 -> 1487 | I18: 7330 | J18: 137833349120
A19: 44377 | B19: 9975 | C19: =+LN(B19/B20) -> 0.10630778 | D19: 3616 | E19: =+B19-D19 -> 6359 | F19: =+E19/B19 -> 0.63749373 | G19: 1796 | H19: =+B19-E19-G19 -> 1820 | I19: 7546 | J19: 126801641472
A20: 44286 | B20: 8969 | C20: =+LN(B20/B21) -> -0.17600216 | D20: 3223 | E20: =+B20-D20 -> 5746 | F20: =+E20/B20 -> 0.64065113 | G20: 1802 | H20: =+B20-E20-G20 -> 1421 | I20: 2393 | J20: 110736465920
A21: 44196 | B21: 10695 | C21: =+LN(B21/B22) -> 0.094768017 | D21: 3714 | E21: =+B21-D21 -> 6981 | F21: =+E21/B21 -> 0.65273492 | G21: 1577 | H21: =+B21-E21-G21 -> 2137 | I21: 3867
A22: 44104 | B22: 9728 | C22: =+LN(B22/B23) -> -0.072072008 | D22: 3298 | E22: =+B22-D22 -> 6430 | F22: =+E22/B22 -> 0.66097862 | G22: 1893 | H22: =+B22-E22-G22 -> 1405 | I22: 4251 | J22: 83387916288
A23: 44012 | B23: 10455 | C23: =+LN(B23/B24) -> -0.012829827 | D23: 3483 | E23: =+B23-D23 -> 6972 | F23: =+E23/B23 -> 0.66685796 | G23: 2061 | H23: =+B23-E23-G23 -> 1422 | I23: 4670 | J23: 85736873984
A24: 43921 | B24: 10590 | C24: =+LN(B24/B25) -> -0.20226613 | D24: 3763 | E24: =+B24-D24 -> 6827 | F24: =+E24/B24 -> 0.64466478 | G24: 2016 | H24: =+B24-E24-G24 -> 1747 | I24: 7423 | J24: 72251351040
A25: 43830 | B25: 12964 | C25: =+LN(B25/B26) -> 0.072613824 | D25: 4329 | E25: =+B25-D25 -> 8635 | F25: =+E25/B25 -> 0.66607529 | G25: 2628 | H25: =+B25-E25-G25 -> 1701 | I25: 8303
A26: 43738 | B26: 12056 | C26: =+LN(B26/B27) -> 0.06131435 | D26: 4038 | E26: =+B26-D26 -> 8018 | F26: =+E26/B26 -> 0.66506304 | G26: 2363 | H26: =+B26-E26-G26 -> 1675 | I26: 7016 | J26: 81500364800
A27: 43646 | B27: 11339 | C27: =+LN(B27/B28) -> 0.10998654 | D27: 3812 | E27: =+B27-D27 -> 7527 | F27: =+E27/B27 -> 0.66381515 | G27: 2299 | H27: =+B27-E27-G27 -> 1513 | I27: 9524
A28: 43555 | B28: 10158 | C28: =+LN(B28/B29) -> -0.098455455 | D28: 3604 | E28: =+B28-D28 -> 6554 | F28: =+E28/B28 -> 0.64520575 | G28: 1941 | H28: =+B28-E28-G28 -> 1663 | I28: 8254
A29: 43465 | B29: 11209 | C29: =+LN(B29/B30) -> 0.101117 | D29: 3719 | E29: =+B29-D29 -> 7490 | F29: =+E29/B29 -> 0.66821304 | G29: 1962 | H29: =+B29-E29-G29 -> 1757 | I29: 7115
A30: 43373 | B30: 10131 | C30: =+LN(B30/B31) -> -0.033391436 | D30: 3443 | E30: =+B30-D30 -> 6688 | F30: =+E30/B30 -> 0.66015201 | G30: 1924 | H30: =+B30-E30-G30 -> 1519 | I30: 7834
A31: 43281 | B31: 10475 | C31: =+LN(B31/B32) -> 0.16846102 | D31: 3441 | E31: =+B31-D31 -> 7034 | F31: =+E31/B31 -> 0.67150358 | G31: 1879 | H31: =+B31-E31-G31 -> 1562 | I31: 8743
A32: 43190 | B32: 8851 | C32: =+LN(B32/B33) -> -0.13319239 | D32: 3133 | E32: =+B32-D32 -> 5718 | F32: =+E32/B32 -> 0.6460287 | G32: 1715 | H32: =+B32-E32-G32 -> 1418 | I32: 7914
A33: 43100 | B33: 10112 | C33: =+LN(B33/B34) -> 0.21337634 | D33: 3439 | E33: =+B33-D33 -> 6673 | F33: =+E33/B33 -> 0.65990902 | G33: 1781 | H33: =+B33-E33-G33 -> 1658 | I33: 8313
A34: 43008 | B34: 8169 | C34: =+LN(B34/B35) -> -0.086490982 | D34: 2764 | E34: =+B34-D34 -> 5405 | F34: =+E34/B34 -> 0.66164769 | G34: 1451 | H34: =+B34-E34-G34 -> 1313 | I34: 9199
A35: 42916 | B35: 8907 | C35: =+LN(B35/B36) -> 0.091768687 | D35: 2977 | E35: =+B35-D35 -> 5930 | F35: =+E35/B35 -> 0.6657685 | G35: 1563 | H35: =+B35-E35-G35 -> 1414 | I35: 10050 | J35: 72314273792
A36: 42825 | B36: 8126 | C36: =+LN(B36/B37) -> -0.19786992 | D36: 2755 | E36: =+B36-D36 -> 5371 | F36: =+E36/B36 -> 0.6609648 | G36: 1433 | H36: =+B36-E36-G36 -> 1322 | I36: 8904 | J36: 70930063360
A37: 42735 | B37: 9904 | C37: =+LN(B37/B38) -> 0.14338826 | D37: 3056 | E37: =+B37-D37 -> 6848 | F37: =+E37/B37 -> 0.6914378 | G37: 1330 | H37: =+B37-E37-G37 -> 1726 | I37: 9731
A38: 42643 | B38: 8581 | C38: =+LN(B38/B39) -> -0.042103075 | D38: 2245 | E38: =+B38-D38 -> 6336 | F38: =+E38/B38 -> 0.73837548 | G38: 365 | H38: =+B38-E38-G38 -> 1880 | I38: 11195 | J38: 56416874496
A39: 42551 | B39: 8950 | C39: =+LN(B39/B40) -> 0.087641337 | D39: 2982 | E39: =+B39-D39 -> 5968 | F39: =+E39/B39 -> 0.66681564 | G39: 1545 | H39: =+B39-E39-G39 -> 1437 | I39: 11768 | J39: 55368237056
A40: 42460 | B40: 8199 | C40: =+LN(B40/B41) -> -0.27599679 | D40: 2770 | E40: =+B40-D40 -> 5429 | F40: =+E40/B40 -> 0.66215392 | G40: 1488 | H40: =+B40-E40-G40 -> 1282 | I40: 10833 | J40: 55745744896
A41: 42369 | B41: 10805 | C41: =+LN(B41/B42) -> 0.10860501 | D41: 3428 | E41: =+B41-D41 -> 7377 | F41: =+E41/B41 -> 0.68273947 | G41: 1944 | H41: =+B41-E41-G41 -> 1484 | I41: 11778
A42: 42277 | B42: 9693 | C42: =+LN(B42/B43) -> -0.048726297 | D42: 3135 | E42: =+B42-D42 -> 6558 | F42: =+E42/B42 -> 0.67657072 | G42: 1830 | H42: =+B42-E42-G42 -> 1305 | I42: 13639 | J42: 57423572992
A43: 42185 | B43: 10177 | C43: =+LN(B43/B44) -> 0.11504776 | D43: 3420 | E43: =+B43-D43 -> 6757 | F43: =+E43/B43 -> 0.66394812 | G43: 1972 | H43: =+B43-E43-G43 -> 1448 | I43: 14195 | J43: 61198680064
A44: 42094 | B44: 9071 | C44: =+LN(B44/B45) -> -0.17214612 | D44: 3056 | E44: =+B44-D44 -> 6015 | F44: =+E44/B44 -> 0.66310219 | G44: 1724 | H44: =+B44-E44-G44 -> 1332 | I44: 13935 | J44: 71097851904
A45: 42004 | B45: 10775 | C45: =+LN(B45/B46) -> 0.15022953 | D45: 3415 | E45: =+B45-D45 -> 7360 | F45: =+E45/B45 -> 0.68306265 | G45: 2109 | H45: =+B45-E45-G45 -> 1306 | I45: 15193
A46: 41912 | B46: 9272 | C46: =+LN(B46/B47) -> 0.096033047 | D46: 2988 | E46: =+B46-D46 -> 6284 | F46: =+E46/B46 -> 0.67773943 | G46: 1437 | H46: =+B46-E46-G46 -> 1551 | I46: 15400 | J46: 64764055552
A47: 41820 | B47: 8423 | C47: =+LN(B47/B48) -> 0.24435106 | D47: 2862 | E47: =+B47-D47 -> 5561 | F47: =+E47/B47 -> 0.66021608 | G47: 1477 | H47: =+B47-E47-G47 -> 1385 | I47: 15951 | J47: 72230379520
A48: 41729 | B48: 6597 | C48: =+LN(B48/B49) -> -0.26619317 | D48: 2455 | E48: =+B48-D48 -> 4142 | F48: =+E48/B48 -> 0.62786115 | G48: 1114 | H48: =+B48-E48-G48 -> 1341 | I48: 1251 | J48: 73446801408
A49: 41639 | B49: 8609 | C49: =+LN(B49/B50) -> 0.18262361 | D49: 2987 | E49: =+B49-D49 -> 5622 | F49: =+E49/B49 -> 0.65303752 | G49: 1522 | H49: =+B49-E49-G49 -> 1465 | I49: 2671
A50: 41547 | B50: 7172 | C50: =+LN(B50/B51) -> -0.046716467 | D50: 2486 | E50: =+B50-D50 -> 4686 | F50: =+E50/B50 -> 0.65337423 | G50: 1310 | H50: =+B50-E50-G50 -> 1176 | I50: 3582 | J50: 65057677312
A51: 41455 | B51: 7515 | C51: =+LN(B51/B52) -> 0.14432991 | D51: 2709 | E51: =+B51-D51 -> 4806 | F51: =+E51/B51 -> 0.63952096 | G51: 1348 | H51: =+B51-E51-G51 -> 1361 | I51: 3707
A52: 41364 | B52: 6505 | C52: =+LN(B52/B53) -> -0.22163588 | D52: 2352 | E52: =+B52-D52 -> 4153 | F52: =+E52/B52 -> 0.63843198 | G52: 1180 | H52: =+B52-E52-G52 -> 1172 | I52: 2509
A53: 41274 | B53: 8119 | C53: =+LN(B53/B54) -> 0.14089573 | D53: 2883 | E53: =+B53-D53 -> 5236 | F53: =+E53/B53 -> 0.64490701 | G53: 1404 | H53: =+B53-E53-G53 -> 1479 | I53: 3593
A54: 41182 | B54: 7052 | C54: =+LN(B54/B55) -> -0.10222173 | D54: 2485 | E54: =+B54-D54 -> 4567 | F54: =+E54/B54 -> 0.6476177 | G54: 1287 | H54: =+B54-E54-G54 -> 1198 | I54: 2997
A55: 41090 | B55: 7811 | C55: =+LN(B55/B56) -> 0.13406192 | D55: 2769 | E55: =+B55-D55 -> 5042 | F55: =+E55/B55 -> 0.64549994 | G55: 1401 | H55: =+B55-E55-G55 -> 1368 | I55: 3609
A56: 40999 | B56: 6831 | C56: =+LN(B56/B57) -> -0.17642414 | D56: 2507 | E56: =+B56-D56 -> 4324 | F56: =+E56/B56 -> 0.63299663 | G56: 1238 | H56: =+B56-E56-G56 -> 1269 | I56: 2080
A57: 40908 | B57: 8149 | C57: =+LN(B57/B58) -> 0.073570061 | D57: 2972 | E57: =+B57-D57 -> 5177 | F57: =+E57/B57 -> 0.63529267 | G57: 1417 | H57: =+B57-E57-G57 -> 1555 | I57: 2629
A58: 40816 | B58: 7571 | C58: =+LN(B58/B59) -> 0.073711802 | D58: 2772 | E58: =+B58-D58 -> 4799 | F58: =+E58/B58 -> 0.63386607 | G58: 1550 | H58: =+B58-E58-G58 -> 1222 | I58: 3354 | J58: 45804625920
A59: 40724 | B59: 7033 | C59: =+LN(B59/B60) -> 0.17583051 | D59: 2779 | E59: =+B59-D59 -> 4254 | F59: =+E59/B59 -> 0.60486279 | G59: 1361 | H59: =+B59-E59-G59 -> 1418 | I59: 4059 | J59: 57171894272
A60: 40633 | B60: 5899 | C60: =+LN(B60/B61) -> -0.19498333 | D60: 2300 | E60: =+B60-D60 -> 3599 | F60: =+E60/B60 -> 0.61010341 | G60: 1238 | H60: =+B60-E60-G60 -> 1062 | I60: -1831 | J60: 57861615616
A61: 40543 | B61: 7169 | C61: =+LN(B61/B62) -> 0.2100135 | D61: 2733 | E61: =+B61-D61 -> 4436 | F61: =+E61/B61 -> 0.61877528 | G61: 1466 | H61: =+B61-E61-G61 -> 1267 | I61: -1319
A62: 40451 | B62: 5811 | C62: =+LN(B62/B63) -> -0.090118459 | D62: 2333 | E62: =+B62-D62 -> 3478 | F62: =+E62/B62 -> 0.59852005 | G62: 1244 | H62: =+B62-E62-G62 -> 1089 | I62: -1253 | J62: 49842864128
A63: 40359 | B63: 6359 | C63: =+LN(B63/B64) -> 0.1669969 | D63: 2422 | E63: =+B63-D63 -> 3937 | F63: =+E63/B63 -> 0.6191225 | G63: 1373 | H63: =+B63-E63-G63 -> 1049 | I63: -472 | J63: 43132436480
A64: 40268 | B64: 5381 | D64: 2203 | E64: =+B64-D64 -> 3178 | F64: =+E64/B64 -> 0.59059654 | G64: 1114 | H64: =+B64-E64-G64 -> 1089 | I64: -1036 | J64: 44862795776

Sheet ALFA - Cost
A1: SUMMARY OUTPUT
A3: Regression Statistics
A4: Multiple R | B4: 0.87675448
A5: R Square | B5: 0.76869842
A6: Adjusted R Square | B6: 0.76441505
A7: Standard Error | B7: 177.83946
A8: Observations | B8: 56
A10: ANOVA
B11: df | C11: SS | D11: MS | E11: F | F11: Significance F
A12: Regression | B12: 1 | C12: 5675804.2 | D12: 5675804.2 | E12: 179.46144 | F12: 8.3439714e-19
A13: Residual | B13: 54 | C13: 1707851.2 | D13: 31626.874
A14: Total | B14: 55 | C14: 7383655.4
B16: Coefficients | C16: Standard Error | D16: t Stat | E16: P-value | F16: Lower 95% | G16: Upper 95% | H16: Lower 95.0% | I16: Upper 95.0%
A17: Intercept | B17: 406.04968 | C17: 89.349727 | D17: 4.5444983 | E17: 3.1392245e-05 | F17: 226.91426 | G17: 585.1851 | H17: 226.91426 | I17: 585.1851
A18: X Variable 1 | B18: 0.1187688 | C18: 0.0088657772 | D18: 13.396322 | E18: 8.3439714e-19 | F18: 0.10099399 | G18: 0.13654362 | H18: 0.10099399 | I18: 0.13654362

Sheet ALFA - Params
A2: Calibration Model
A3: R_0 | B3: =+'ALFA - FA'!B60*4 -> 23596
A4: mu_0 | B4: =+AVERAGE('ALFA - FA'!C60:C63)*4 -> 0.091908615
A5: sigma | B5: =+_xlfn.STDEV.S('ALFA - FA'!C9:C63)/0.5 -> 0.28340998
A6: theta | B6: =+AVERAGE('ALFA - FA'!F9:F64) -> 0.65382334
A7: gamma | B7: =+'ALFA - Cost'!B18 -> 0.1187688 | C7: =+'ALFA - Cost'!E18 -> 8.3439714e-19 | D7: R2 | E7: =+'ALFA - Cost'!B5 -> 0.76869842
A8: F | B8: =+'ALFA - Cost'!B17 -> 406.04968 | C8: =+'ALFA - Cost'!E17 -> 3.1392245e-05 | D8: N | E8: =+'ALFA - Cost'!B8 -> 56
A9: sigma_stock | B9: =+SQRT(252*_xlfn.VAR.S(ALFA!C:C)) -> 0.28324384
A11: Simulation Model
A12: R_0 | B12: =+'ALFA - FA'!B9*4 -> 71356
A13: mu_0 | B13: =+AVERAGE('ALFA - FA'!C9:C13)*4 -> 0.24190648
A14: sigma | B14: =+B5 -> 0.28340998
A15: theta | B15: =+B6 -> 0.65382334
A16: gamma | B16: =+B7 -> 0.1187688
A17: F | B17: =+B8 -> 406.04968
A18: eta

Sheet REC
A1: Date | B1: Last Price (R1) | C1: Log-Returns
A2: 46072 | B2: 47.94 | C2: =+LN(B2/B3) -> -0.011613569
A3: 46071 | B3: 48.5 | C3: =+LN(B3/B4) -> 0.024208194
A4: 46070 | B4: 47.34 | C4: =+LN(B4/B5) -> -0.00084459464
A5: 46069 | B5: 47.38 | C5: =+LN(B5/B6) -> -0.010915306
A6: 46066 | B6: 47.9 | C6: =+LN(B6/B7) -> 0.010493276
A7: 46065 | B7: 47.4 | C7: =+LN(B7/B8) -> -0.001686341
A8: 46064 | B8: 47.48 | C8: =+LN(B8/B9) -> -0.0071353923
A9: 46063 | B9: 47.82 | C9: =+LN(B9/B10) -> 0.014322065
A10: 46062 | B10: 47.14 | C10: =+LN(B10/B11) -> -0.0012719951
A11: 46059 | B11: 47.2 | C11: =+LN(B11/B12) -> -0.016807118
A12: 46058 | B12: 48 | C12: =+LN(B12/B13) -> -0.0041580101
A13: 46057 | B13: 48.2 | C13: =+LN(B13/B14) -> 0.0058260672
... A4341: 39833 | B4341: 3.85 | C4341: =+LN(B4341/B4342) -> 0.019672766
A4342: 39832 | B4342: 3.775

Sheet REC - FA
A1: Quarter | B1: Revenue | C1: Log-Growth | D1: Gross Profit | E1: COGS | F1: COGS Margin | G1: EBITDA | H1: OpEx | I1: Net Debt (R2) | J1: Current Market Cap (L2)
A2: 45930 | B2: 632.321 | C2: =+LN(B2/B3) -> -0.018118303 | D2: 432.408 | E2: =+B2-D2 -> 199.913 | F2: =+E2/B2 -> 0.31615746 | G2: 216.779 | H2: =+B2-E2-G2 -> 215.629 | I2: 2033.507 | J2: 10811770880
A3: 45838 | B3: 643.882 | C3: =+LN(B3/B4) -> -0.054518493 | D3: 423.85 | E3: =+B3-D3 -> 220.032 | F3: =+E3/B3 -> 0.34172721 | G3: 185.986 | H3: =+B3-E3-G3 -> 237.864 | I3: 2130.186 | J3: 11167283200
A4: 45747 | B4: 679.96 | C4: =+LN(B4/B5) -> 0.12764421 | D4: 458.772 | E4: =+B4-D4 -> 221.188 | F4: =+E4/B4 -> 0.32529561 | G4: 246.688 | H4: =+B4-E4-G4 -> 212.084 | I4: 2025.8669 | J4: 10937245696
A5: 45657 | B5: 598.478 | C5: =+LN(B5/B6) -> 0.071081534 | D5: 413.362 | E5: =+B5-D5 -> 185.116 | F5: =+E5/B5 -> 0.30931129 | G5: 180.19 | H5: =+B5-E5-G5 -> 233.172 | I5: 2162.0039
A6: 45565 | B6: 557.414 | C6: =+LN(B6/B7) -> -0.036000896 | D6: 385.124 | E6: =+B6-D6 -> 172.29 | F6: =+E6/B6 -> 0.30908804 | G6: 206.694 | H6: =+B6-E6-G6 -> 178.43 | I6: 1322.631 | J6: 10623557632
A7: 45473 | B7: 577.847 | C7: =+LN(B7/B8) -> -0.050569658 | D7: 386.226 | E7: =+B7-D7 -> 191.621 | F7: =+E7/B7 -> 0.331612 | G7: 192.11 | H7: =+B7-E7-G7 -> 194.116 | I7: 1477.068
A8: 45382 | B8: 607.82 | C8: =+LN(B8/B9) -> 0.14427914 | D8: 415.56 | E8: =+B8-D8 -> 192.26 | F8: =+E8/B8 -> 0.31631075 | G8: 226.888 | H8: =+B8-E8-G8 -> 188.672 | I8: 1439.489
A9: 45291 | B9: 526.157 | C9: =+LN(B9/B10) -> 0.027466447 | D9: 356.945 | E9: =+B9-D9 -> 169.212 | F9: =+E9/B9 -> 0.32159983 | G9: 158.046 | H9: =+B9-E9-G9 -> 198.899 | I9: 1587.088
A10: 45199 | B10: 511.902 | C10: =+LN(B10/B11) -> 0.037808628 | D10: 333.361 | E10: =+B10-D10 -> 178.541 | F10: =+E10/B10 -> 0.34877965 | G10: 161.256 | H10: =+B10-E10-G10 -> 172.105 | I10: 1513.516
A11: 45107 | B11: 492.909 | C11: =+LN(B11/B12) -> -0.11206882 | D11: 344.609 | E11: =+B11-D11 -> 148.3 | F11: =+E11/B11 -> 0.30086689 | G11: 174.619 | H11: =+B11-E11-G11 -> 169.99 | I11: 1336.0959 | J11: 9149225984
A12: 45016 | B12: 551.363 | C12: =+LN(B12/B13) -> 0.14746936 | D12: 387.709 | E12: =+B12-D12 -> 163.654 | F12: =+E12/B12 -> 0.29681716 | G12: 206.757 | H12: =+B12-E12-G12 -> 180.952 | I12: 1349.548 | J12: 8147515904
A13: 44926 | B13: 475.765 | C13: =+LN(B13/B14) -> -0.019332067 | D13: 331.832 | E13: =+B13-D13 -> 143.933 | F13: =+E13/B13 -> 0.30252961 | G13: 116.963 | H13: =+B13-E13-G13 -> 214.869 | I13: 1431.786
A14: 44834 | B14: 485.052 | C14: =+LN(B14/B15) -> 0.024930296 | D14: 330.128 | E14: =+B14-D14 -> 154.924 | F14: =+E14/B14 -> 0.31939668 | G14: 156.638 | H14: =+B14-E14-G14 -> 173.49 | I14: 1353.719 | J14: 7881927168
A15: 44742 | B15: 473.109 | C15: =+LN(B15/B16) -> 0.12054599 | D15: 320.707 | E15: =+B15-D15 -> 152.402 | F15: =+E15/B15 -> 0.32212873 | G15: 133.559 | H15: =+B15-E15-G15 -> 187.148 | I15: 1454.14 | J15: 8680784896
A16: 44651 | B16: 419.381 | C16: =+LN(B16/B17) -> -0.010682377 | D16: 303.903 | E16: =+B16-D16 -> 115.478 | F16: =+E16/B16 -> 0.27535344 | G16: 155.922 | H16: =+B16-E16-G16 -> 147.981 | I16: 1409.448 | J16: 9544472576
A17: 44561 | B17: 423.885 | C17: =+LN(B17/B18) -> 0.0952998 | D17: 309.163 | E17: =+B17-D17 -> 114.722 | F17: =+E17/B17 -> 0.27064416 | G17: 141.952 | H17: =+B17-E17-G17 -> 167.211 | I17: 746.138
A18: 44469 | B18: 385.354 | C18: =+LN(B18/B19) -> -0.0016672051 | D18: 278.289 | E18: =+B18-D18 -> 107.065 | F18: =+E18/B18 -> 0.27783544 | G18: 146.949 | H18: =+B18-E18-G18 -> 131.34 | I18: 724.421 | J18: 10514812928
A19: 44377 | B19: 385.997 | C19: =+LN(B19/B20) -> 0.0030071309 | D19: 284.126 | E19: =+B19-D19 -> 101.871 | F19: =+E19/B19 -> 0.26391656 | G19: 149.627 | H19: =+B19-E19-G19 -> 134.499 | I19: 875.69 | J19: 10079832064
A20: 44286 | B20: 384.838 | C20: =+LN(B20/B21) -> 0.080566658 | D20: 280.769 | E20: =+B20-D20 -> 104.069 | F20: =+E20/B20 -> 0.27042288 | G20: 149.247 | H20: =+B20-E20-G20 -> 131.522 | I20: 861.297 | J20: 9592570880
A21: 44196 | B21: 355.049 | C21: =+LN(B21/B22) -> 0.062235203 | D21: 256.455 | E21: =+B21-D21 -> 98.594 | F21: =+E21/B21 -> 0.27769125 | G21: 129.069 | H21: =+B21-E21-G21 -> 127.386 | I21: 872.829
A22: 44104 | B22: 333.626 | C22: =+LN(B22/B23) -> 0.0080321475 | D22: 237.143 | E22: =+B22-D22 -> 96.483 | F22: =+E22/B22 -> 0.28919509 | G22: 126.487 | H22: =+B22-E22-G22 -> 110.656 | I22: 856.023 | J22: 9147133952
A23: 44012 | B23: 330.957 | C23: =+LN(B23/B24) -> -0.2600161 | D23: 244.714 | E23: =+B23-D23 -> 86.243 | F23: =+E23/B23 -> 0.26058672 | G23: 136.277 | H23: =+B23-E23-G23 -> 108.437 | I23: 936.31 | J23: 9295612928
A24: 43921 | B24: 429.235 | C24: =+LN(B24/B25) -> 0.11807721 | D24: 303.724 | E24: =+B24-D24 -> 125.511 | F24: =+E24/B24 -> 0.29240626 | G24: 170.855 | H24: =+B24-E24-G24 -> 132.869 | I24: 895.997 | J24: 8059683328
A25: 43830 | B25: 381.43 | C25: =+LN(B25/B26) -> 0.065729488 | D25: 273.598 | E25: =+B25-D25 -> 107.832 | F25: =+E25/B25 -> 0.28270456 | G25: 133.902 | H25: =+B25-E25-G25 -> 139.696 | I25: 912.63
A26: 43738 | B26: 357.165 | C26: =+LN(B26/B27) -> -0.0086364604 | D26: 251.394 | E26: =+B26-D26 -> 105.771 | F26: =+E26/B26 -> 0.29614044 | G26: 130.299 | H26: =+B26-E26-G26 -> 121.095 | I26: 510.25 | J26: 8231165952
A27: 43646 | B27: 360.263 | C27: =+LN(B27/B28) -> -0.061174559 | D27: 253.431 | E27: =+B27-D27 -> 106.832 | F27: =+E27/B27 -> 0.29653892 | G27: 135.374 | H27: =+B27-E27-G27 -> 118.057 | I27: 618.981
A28: 43555 | B28: 382.99 | C28: =+LN(B28/B29) -> 0.12222413 | D28: 266.524 | E28: =+B28-D28 -> 116.466 | F28: =+E28/B28 -> 0.30409671 | G28: 143.939 | H28: =+B28-E28-G28 -> 122.585 | I28: 563.681
A29: 43465 | B29: 338.927 | C29: =+LN(B29/B30) -> 0.06608203 | D29: 239.373 | E29: =+B29-D29 -> 99.554 | F29: =+E29/B29 -> 0.29373287 | G29: 119.029 | H29: =+B29-E29-G29 -> 120.344 | I29: 590.099
A30: 43373 | B30: 317.254 | C30: =+LN(B30/B31) -> -0.03803751 | D30: 224.252 | E30: =+B30-D30 -> 93.002 | F30: =+E30/B30 -> 0.29314682 | G30: 120.033 | H30: =+B30-E30-G30 -> 104.219 | I30: 460.856
A31: 43281 | B31: 329.554 | C31: =+LN(B31/B32) -> -0.1062583 | D31: 235.829 | E31: =+B31-D31 -> 93.725 | F31: =+E31/B31 -> 0.28439952 | G31: 125.644 | H31: =+B31-E31-G31 -> 110.185 | I31: 554.073
A32: 43190 | B32: 366.5 | C32: =+LN(B32/B33) -> 0.12234184 | D32: 257.212 | E32: =+B32-D32 -> 109.288 | F32: =+E32/B32 -> 0.29819372 | G32: 134.373 | H32: =+B32-E32-G32 -> 122.839 | I32: 476.076
A33: 43100 | B33: 324.296 | C33: =+LN(B33/B34) -> 0.035584487 | D33: 229.138 | E33: =+B33-D33 -> 95.158 | F33: =+E33/B33 -> 0.29342946 | G33: 112.684 | H33: =+B33-E33-G33 -> 116.454 | I33: 378.672
A34: 43008 | B34: 312.959 | C34: =+LN(B34/B35) -> 0.012963952 | D34: 222.105 | E34: =+B34-D34 -> 90.854 | F34: =+E34/B34 -> 0.2903064 | G34: 117.929 | H34: =+B34-E34-G34 -> 104.176 | I34: 321.642
A35: 42916 | B35: 308.928 | C35: =+LN(B35/B36) -> -0.10152704 | D35: 217.995 | E35: =+B35-D35 -> 90.933 | F35: =+E35/B35 -> 0.29435014 | G35: 106.325 | H35: =+B35-E35-G35 -> 111.67 | I35: 361.436 | J35: 7428125184
A36: 42825 | B36: 341.94 | C36: =+LN(B36/B37) -> 0.15934831 | D36: 236.131 | E36: =+B36-D36 -> 105.809 | F36: =+E36/B36 -> 0.30943733 | G36: 117.707 | H36: =+B36-E36-G36 -> 118.424 | I36: 117.872 | J36: 6643906048
A37: 42735 | B37: 291.572 | C37: =+LN(B37/B38) -> 0.060313855 | D37: 197.914 | E37: =+B37-D37 -> 93.658 | F37: =+E37/B37 -> 0.3212174 | G37: 85.403 | H37: =+B37-E37-G37 -> 112.511 | I37: 211.268
A38: 42643 | B38: 274.506 | C38: =+LN(B38/B39) -> -0.039678634 | D38: 187.677 | E38: =+B38-D38 -> 86.829 | F38: =+E38/B38 -> 0.31631003 | G38: 91.878 | H38: =+B38-E38-G38 -> 95.799 | I38: 110.076 | J38: 5983070720
A39: 42551 | B39: 285.617 | C39: =+LN(B39/B40) -> -0.056592811 | D39: 198.846 | E39: =+B39-D39 -> 86.771 | F39: =+E39/B39 -> 0.30380194 | G39: 89.099 | H39: =+B39-E39-G39 -> 109.747 | I39: 176.258 | J39: 5646379008
A40: 42460 | B40: 302.247 | C40: =+LN(B40/B41) -> 0.13816321 | D40: 208.546 | E40: =+B40-D40 -> 93.701 | F40: =+E40/B40 -> 0.31001466 | G40: 98.975 | H40: =+B40-E40-G40 -> 109.571 | I40: 50.953 | J40: 4600753152
A41: 42369 | B41: 263.244 | C41: =+LN(B41/B42) -> 0.070305932 | D41: 179.682 | E41: =+B41-D41 -> 83.562 | F41: =+E41/B41 -> 0.31743174 | G41: 76.462 | H41: =+B41-E41-G41 -> 103.22 | I41: 101.408
A42: 42277 | B42: 245.372 | C42: =+LN(B42/B43) -> -0.07057181 | D42: 166.013 | E42: =+B42-D42 -> 79.359 | F42: =+E42/B42 -> 0.32342321 | G42: 76.647 | H42: =+B42-E42-G42 -> 89.366 | I42: 58.196 | J42: 4314251776
A43: 42185 | B43: 263.314 | C43: =+LN(B43/B44) -> -0.046132916 | D43: 179.318 | E43: =+B43-D43 -> 83.996 | F43: =+E43/B43 -> 0.31899557 | G43: 81.117 | H43: =+B43-E43-G43 -> 98.201 | I43: 139.864 | J43: 3933644032
A44: 42094 | B44: 275.746 | C44: =+LN(B44/B45) -> 0.11712866 | D44: 187.453 | E44: =+B44-D44 -> 88.293 | F44: =+E44/B44 -> 0.32019685 | G44: 82.774 | H44: =+B44-E44-G44 -> 104.679 | I44: 136.792 | J44: 3638777600
A45: 42004 | B45: 245.268 | C45: =+LN(B45/B46) -> 0.045036637 | D45: 162.999 | E45: =+B45-D45 -> 82.269 | F45: =+E45/B45 -> 0.33542492 | G45: 60.87 | H45: =+B45-E45-G45 -> 102.129
A46: 41912 | B46: 234.467 | C46: =+LN(B46/B47) -> -0.053121517 | D46: 160.72 | E46: =+B46-D46 -> 73.747 | F46: =+E46/B46 -> 0.3145304 | G46: 71.098 | H46: =+B46-E46-G46 -> 89.622 | I46: 152.184 | J46: 2714444544
A47: 41820 | B47: 247.259 | C47: =+LN(B47/B48) -> -0.0516366 | D47: 163.216 | E47: =+B47-D47 -> 84.043 | F47: =+E47/B47 -> 0.33989865 | G47: 70.434 | H47: =+B47-E47-G47 -> 92.782 | I47: 207.99 | J47: 2568056832
A48: 41729 | B48: 260.362 | C48: =+LN(B48/B49) -> 0.083014462 | D48: 173.367 | E48: =+B48-D48 -> 86.995 | F48: =+E48/B48 -> 0.33413094 | G48: 71.416 | H48: =+B48-E48-G48 -> 101.951 | I48: 226.9 | J48: 2655889408
A49: 41639 | B49: 239.621 | C49: =+LN(B49/B50) -> 0.066185531 | D49: 154.207 | E49: =+B49-D49 -> 85.414 | F49: =+E49/B49 -> 0.35645457 | G49: 56.114 | H49: =+B49-E49-G49 -> 98.093 | I49: 258.821
A50: 41547 | B50: 224.275 | C50: =+LN(B50/B51) -> -0.038839069 | D50: 148.02 | E50: =+B50-D50 -> 76.255 | F50: =+E50/B50 -> 0.34000669 | G50: 53.984 | H50: =+B50-E50-G50 -> 94.036 | I50: 132.691 | J50: 1857031296
A51: 41455 | B51: 233.157 | C51: =+LN(B51/B52) -> -0.047818141 | D51: 152.857 | E51: =+B51-D51 -> 80.3 | F51: =+E51/B51 -> 0.34440313 | G51: 58.7 | H51: =+B51-E51-G51 -> 94.157 | I51: 173.245
A52: 41364 | B52: 244.577 | C52: =+LN(B52/B53) -> 0.16189596 | D52: 159.217 | E52: =+B52-D52 -> 85.36 | F52: =+E52/B52 -> 0.34901074 | G52: 61.332 | H52: =+B52-E52-G52 -> 97.885 | I52: 194.345
A53: 41274 | B53: 208.02 | C53: =+LN(B53/B54) -> 0.037553418 | D53: 133.192 | E53: =+B53-D53 -> 74.828 | F53: =+E53/B53 -> 0.35971541 | G53: 40.928 | H53: =+B53-E53-G53 -> 92.264 | I53: 154.827
A54: 41182 | B54: 200.353 | C54: =+LN(B54/B55) -> -0.00015970534 | D54: 129.142 | E54: =+B54-D54 -> 71.211 | F54: =+E54/B54 -> 0.35542767 | G54: 48.527 | H54: =+B54-E54-G54 -> 80.615 | I54: 47.894
A55: 41090 | B55: 200.385 | C55: =+LN(B55/B56) -> -0.091380473 | D55: 130.864 | E55: =+B55-D55 -> 69.521 | F55: =+E55/B55 -> 0.34693715 | G55: 48.23 | H55: =+B55-E55-G55 -> 82.634 | I55: 69.616
A56: 40999 | B56: 219.559 | C56: =+LN(B56/B57) -> 0.19089991 | D56: 141.562 | E56: =+B56-D56 -> 77.997 | F56: =+E56/B56 -> 0.35524392 | G56: 54.026 | H56: =+B56-E56-G56 -> 87.536 | I56: 55.601
A57: 40908 | B57: 181.403 | C57: =+LN(B57/B58) -> 0.0099109717 | D57: 118.271 | E57: =+B57-D57 -> 63.132 | F57: =+E57/B57 -> 0.34802071 | G57: 40.715 | H57: =+B57-E57-G57 -> 77.556 | I57: 57.525
A58: 40816 | B58: 179.614 | C58: =+LN(B58/B59) -> -0.12326742 | D58: 116.308 | E58: =+B58-D58 -> 63.306 | F58: =+E58/B58 -> 0.35245582 | G58: 46.611 | H58: =+B58-E58-G58 -> 69.697 | I58: 31.149 | J58: 1366633216
A59: 40724 | B59: 203.177 | C59: =+LN(B59/B60) -> 0.026608788 | D59: 136.548 | E59: =+B59-D59 -> 66.629 | F59: =+E59/B59 -> 0.32793574 | G59: 49.964 | H59: =+B59-E59-G59 -> 86.584 | I59: -29.911 | J59: 1586214656
A60: 40633 | B60: 197.842 | C60: =+LN(B60/B61) -> 0.09726567 | D60: 130.932 | E60: =+B60-D60 -> 66.91 | F60: =+E60/B60 -> 0.33819917 | G60: 50.452 | H60: =+B60-E60-G60 -> 80.48 | I60: -38.782 | J60: 1483743232
A61: 40543 | B61: 179.505 | C61: =+LN(B61/B62) -> 0.04058294 | D61: 118.93 | E61: =+B61-D61 -> 60.575 | F61: =+E61/B61 -> 0.33745578 | G61: 37.819 | H61: =+B61-E61-G61 -> 81.111 | I61: -44.803
A62: 40451 | B62: 172.366 | C62: =+LN(B62/B63) -> -0.099543763 | D62: 114.266 | E62: =+B62-D62 -> 58.1 | F62: =+E62/B62 -> 0.33707344 | G62: 46.003 | H62: =+B62-E62-G62 -> 68.263 | I62: -17.298 | J62: 1373952512
A63: 40359 | B63: 190.407 | C63: =+LN(B63/B64) -> 0.024191706 | D63: 128.716 | E63: =+B63-D63 -> 61.691 | F63: =+E63/B63 -> 0.32399544 | G63: 48.202 | H63: =+B63-E63-G63 -> 80.514 | I63: 26.743 | J63: 1205606784
A64: 40268 | B64: 185.856 | D64: 126.157 | E64: =+B64-D64 -> 59.699 | F64: =+E64/B64 -> 0.32121105 | G64: 49.71 | H64: =+B64-E64-G64 -> 76.447 | I64: 3.747 | J64: 1174940928

Sheet REC - Cost
A1: SUMMARY OUTPUT
A3: Regression Statistics
A4: Multiple R | B4: 0.95233294
A5: R Square | B5: 0.90693803
A6: Adjusted R Square | B6: 0.90521466
A7: Standard Error | B7: 10.347508
A8: Observations | B8: 56
A10: ANOVA
B11: df | C11: SS | D11: MS | E11: F | F11: Significance F
A12: Regression | B12: 1 | C12: 56346.983 | D12: 56346.983 | E12: 526.25852 | F12: 1.6255559e-29
A13: Residual | B13: 54 | C13: 5781.8297 | D13: 107.07092
A14: Total | B14: 55 | C14: 62128.813
B16: Coefficients | C16: Standard Error | D16: t Stat | E16: P-value | F16: Lower 95% | G16: Upper 95% | H16: Lower 95.0% | I16: Upper 95.0%
A17: Intercept | B17: 15.971594 | C17: 4.5451043 | D17: 3.5140213 | E17: 0.00090145855 | F17: 6.859208 | G17: 25.083979 | H17: 6.859208 | I17: 25.083979
A18: X Variable 1 | B18: 0.31718625 | C18: 0.01382658 | D18: 22.940325 | E18: 1.6255559e-29 | F18: 0.28946563 | G18: 0.34490688 | H18: 0.28946563 | I18: 0.34490688

Sheet REC - Params
A2: Calibration Model
A3: R_0 | B3: =+'REC - FA'!B60*4 -> 791.368
A4: mu_0 | B4: =+AVERAGE('REC - FA'!C60:C63)*4 -> 0.062496552
A5: sigma | B5: =+_xlfn.STDEV.S('REC - FA'!C9:C63)/0.5 -> 0.17462596
A6: theta | B6: =+AVERAGE('REC - FA'!F9:F64) -> 0.31384946
A7: gamma | B7: =+'REC - Cost'!B18 -> 0.31718625 | C7: =+'REC - Cost'!E18 -> 1.6255559e-29 | D7: R2 | E7: =+'REC - Cost'!B5 -> 0.90693803
A8: F | B8: =+'REC - Cost'!B17 -> 15.971594 | C8: =+'REC - Cost'!E17 -> 0.00090145855 | D8: N | E8: =+'REC - Cost'!B8 -> 56
A9: sigma_stock | B9: =+SQRT(252*_xlfn.VAR.S(REC!C:C)) -> 0.25376751
A11: Simulation Model
A12: R_0 | B12: =+'REC - FA'!B9*4 -> 2104.628
A13: mu_0 | B13: =+AVERAGE('REC - FA'!C9:C13)*4 -> 0.065074836
A14: sigma | B14: =+B5 -> 0.17462596
A15: theta | B15: =+B6 -> 0.31384946
A16: gamma | B16: =+B7 -> 0.31718625
A17: F | B17: =+B8 -> 15.971594
A18: eta
